{
  "task": "swinir_sr_x2_Obstacles_no_umass_Outdoor"    
  , "model": "plain" 
  , "gpu_ids": [0]
  , "dist": true

  , "scale": 2     
  , "n_channels": 3

  , "path": {
    "root": "superresolution"            
    , "pretrained_netG": null      
    , "pretrained_netE": null      
  }

  , "datasets": {
    "train": {
      "name": "train_dataset"  
     , "dataset_type": "sr"          
      , "dataroot_H": "/home/vittorio/Scrivania/ETH/Upsampling/Upsampling_CFD/datasets/Split_Outdoor_Flow/train/high_res"
      , "dataroot_L": "/home/vittorio/Scrivania/ETH/Upsampling/Upsampling_CFD/datasets/Split_Outdoor_Flow/train/low_res"
        

      , "H_size": 64
      ,"lq_patchsize": 8
      , "dataloader_shuffle": true
      , "dataloader_num_workers": 16
      , "dataloader_batch_size": 4
    }
    , "test": {
      "name": "test_dataset"            
      , "dataset_type": "sr"         
      , "dataroot_H": "/home/vittorio/Scrivania/ETH/Upsampling/Upsampling_CFD/datasets/Split_Outdoor_Flow/test/high_res"
      , "dataroot_L": "/home/vittorio/Scrivania/ETH/Upsampling/Upsampling_CFD/datasets/Split_Outdoor_Flow/test/low_res"
    }
  }

  , "netG": {
    "net_type": "swinir" 
    , "upscale": 2                   
    , "in_chans": 3
    , "img_size": 32                   
    , "window_size": 8
    , "img_range": 1.0 
    , "depths": [6, 6, 6, 6, 6, 6] 
    , "embed_dim": 180 
    , "num_heads": [6, 6, 6, 6, 6, 6]
    , "mlp_ratio": 2 
    , "upsampler": "pixelshuffle"       
    , "resi_connection": "1conv"        
    ,  "scale": 2

    , "init_type": "default"
  }


  , "train": {
    "G_lossfn_type": "l1"
    ,"use_umass_loss": false
    , "use_mask": true
    , "umass_loss_weight":2
    ,"use_dissipation_loss": false
    ,"dissipation_loss_weight": 0.25
    , "G_lossfn_weight": 1         

    , "E_decay": 0.999
    ,"diff_vel_dir": "superresolution/swinir_sr_classical_patch24_x4_physic_mass_1_no_pad/diff_velocities"
    ,"pred_vel_dir": "superresolution/swinir_sr_classical_patch24_x4_physic_mass_1_no_pad/pred_velocities"
    ,"save_heatmaps": false             

    , "G_optimizer_type": "adam"        
    , "G_optimizer_lr": 5e-5            
    , "G_optimizer_wd": 0               
    , "G_optimizer_clipgrad": null      
    , "G_optimizer_reuse": true         

    , "G_scheduler_type": "MultiStepLR" 
    , "G_scheduler_milestones": [250000, 400000, 450000, 475000, 500000]
    , "G_scheduler_gamma": 0.5

    , "G_regularizer_orthstep": null    
    , "G_regularizer_clipstep": null   

    , "G_param_strict": true
    , "E_param_strict": true

    , "checkpoint_test": 2000         
    , "checkpoint_save": 2000           
    , "checkpoint_print": 250
  }
}
